environment_loader/__init__.py
environment_loader/environment.py
environment_loader-1.0.0.dist-info/METADATA
environment_loader-1.0.0.dist-info/WHEEL
environment_loader-1.0.0.dist-info/top_level.txt
environment_loader-1.0.0.dist-info/RECORD
