Metadata-Version: 2.1
Name: environment-loader
Version: 1.0.0
Summary: A simple class to verify environment variables & get environment variables while avoiding typos.
Author-email: Ghazanfar Shahbaz <ghazanfarshahbaz2409@gmail.com>
Project-URL: Homepage, https://github.com/GhazTools/EnvironmentLoader
Classifier: Programming Language :: Python :: 3
Classifier: License :: OSI Approved :: MIT License
Classifier: Operating System :: OS Independent
Requires-Python: >=3.11
Requires-Dist: python-dotenv ==1.0.1
